ss_fasttext_langdetector/__init__.py
ss_fasttext_langdetector-0.0.3.dist-info/METADATA
ss_fasttext_langdetector-0.0.3.dist-info/WHEEL
ss_fasttext_langdetector-0.0.3.dist-info/RECORD
