Metadata-Version: 2.4
Name: ss-fasttext-langdetector
Version: 0.0.3
Summary: FastText Language Detector
Project-URL: Homepage, https://github.com/shern2/ss-fasttext-langdetector
Project-URL: Repository, https://github.com/shern2/ss-fasttext-langdetector
Project-URL: Issues, https://github.com/shern2/ss-fasttext-langdetector/issues
Author: shern
License: MIT
Keywords: detector,fasttext,language
Requires-Python: <3.13,>=3.12
Requires-Dist: fasttext==0.9.3
Requires-Dist: platformdirs>=4.3.6
Requires-Dist: tenacity>=9.1.2
